torchfusion/__init__.py
torchfusion/datasets/__init__.py
torchfusion/datasets/datasets.py
torchfusion/fp16_utils/__init__.py
torchfusion/fp16_utils/fp16_optimizer.py
torchfusion/fp16_utils/fp16util.py
torchfusion/fp16_utils/loss_scaler.py
torchfusion/gan/__init__.py
torchfusion/gan/distributions.py
torchfusion/gan/applications/__init__.py
torchfusion/gan/applications/applications.py
torchfusion/gan/layers/__init__.py
torchfusion/gan/layers/layers.py
torchfusion/gan/learners/__init__.py
torchfusion/gan/learners/learners.py
torchfusion/initializers/__init__.py
torchfusion/initializers/initializers.py
torchfusion/lang/__init__.py
torchfusion/lang/datasets/__init__.py
torchfusion/lang/datasets/datasets.py
torchfusion/layers/__init__.py
torchfusion/layers/layers.py
torchfusion/learners/__init__.py
torchfusion/learners/learners.py
torchfusion/metrics/__init__.py
torchfusion/metrics/metrics.py
torchfusion/transforms/__init__.py
torchfusion/transforms/transforms.py
torchfusion/utils/__init__.py
torchfusion/utils/logger.py
torchfusion/utils/utils.py
torchfusion-0.3.6.dist-info/DESCRIPTION.rst
torchfusion-0.3.6.dist-info/METADATA
torchfusion-0.3.6.dist-info/RECORD
torchfusion-0.3.6.dist-info/WHEEL
torchfusion-0.3.6.dist-info/metadata.json
torchfusion-0.3.6.dist-info/top_level.txt
