Metadata-Version: 2.0
Name: torchfusion
Version: 0.3.6
Summary: A modern deep learning framework built to accelerate research and development of AI systems
Home-page: https://github.com/johnolafenwa/TorchFusion
Author: John Olafenwa and Moses Olafenwa
Author-email: UNKNOWN
License: MIT
Platform: UNKNOWN
Classifier: Programming Language :: Python :: 3
Classifier: License :: OSI Approved :: MIT License
Classifier: Operating System :: OS Independent
Requires-Dist: matplotlib
Requires-Dist: numpy
Requires-Dist: tensorboardX
Requires-Dist: torchtext
Requires-Dist: torchvision
Requires-Dist: tqdm
Requires-Dist: visdom
